pysea/__init__.py
pysea-1.0.3.dist-info/METADATA
pysea-1.0.3.dist-info/WHEEL
pysea-1.0.3.dist-info/top_level.txt
pysea-1.0.3.dist-info/RECORD
